odoo/addons/analytic_brand/README.rst
odoo/addons/analytic_brand/__init__.py
odoo/addons/analytic_brand/__manifest__.py
odoo/addons/analytic_brand/i18n/analytic_brand.pot
odoo/addons/analytic_brand/models/__init__.py
odoo/addons/analytic_brand/models/res_brand.py
odoo/addons/analytic_brand/readme/CONTRIBUTORS.rst
odoo/addons/analytic_brand/readme/DESCRIPTION.rst
odoo/addons/analytic_brand/static/description/icon.png
odoo/addons/analytic_brand/static/description/index.html
odoo/addons/analytic_brand/views/res_brand.xml
odoo12_addon_analytic_brand-12.0.1.0.1.dist-info/METADATA
odoo12_addon_analytic_brand-12.0.1.0.1.dist-info/WHEEL
odoo12_addon_analytic_brand-12.0.1.0.1.dist-info/top_level.txt
odoo12_addon_analytic_brand-12.0.1.0.1.dist-info/RECORD
